moses/__init__.py
moses/interfaces.py
moses/models_storage.py
moses/script_utils.py
moses/utils.py
moses/aae/__init__.py
moses/aae/config.py
moses/aae/model.py
moses/aae/trainer.py
moses/baselines/__init__.py
moses/baselines/combinatorial.py
moses/baselines/hmm.py
moses/baselines/ngram.py
moses/char_rnn/__init__.py
moses/char_rnn/config.py
moses/char_rnn/model.py
moses/char_rnn/trainer.py
moses/dataset/__init__.py
moses/dataset/dataset.py
moses/dataset/data/test.csv.gz
moses/dataset/data/test_scaffolds.csv.gz
moses/dataset/data/test_scaffolds_stats.npz
moses/dataset/data/test_stats.npz
moses/dataset/data/train.csv.gz
moses/latentgan/__init__.py
moses/latentgan/config.py
moses/latentgan/model.py
moses/latentgan/trainer.py
moses/metrics/__init__.py
moses/metrics/mcf.csv
moses/metrics/metrics.py
moses/metrics/utils.py
moses/metrics/wehi_pains.csv
moses/metrics/NP_Score/__init__.py
moses/metrics/NP_Score/npscorer.py
moses/metrics/NP_Score/publicnp.model.gz
moses/metrics/SA_Score/UnitTestSAScore.py
moses/metrics/SA_Score/__init__.py
moses/metrics/SA_Score/fpscores.pkl.gz
moses/metrics/SA_Score/sascorer.py
moses/organ/__init__.py
moses/organ/config.py
moses/organ/metrics_reward.py
moses/organ/model.py
moses/organ/trainer.py
moses/vae/__init__.py
moses/vae/config.py
moses/vae/misc.py
moses/vae/model.py
moses/vae/trainer.py
tests/__init__.py
tests/test_baselines.py
tests/test_metrics.py
molsets-0.3.1.dist-info/LICENSE
molsets-0.3.1.dist-info/METADATA
molsets-0.3.1.dist-info/WHEEL
molsets-0.3.1.dist-info/top_level.txt
molsets-0.3.1.dist-info/RECORD
