Metadata-Version: 2.1
Name: molsets
Version: 0.3.1
Summary: Molecular Sets (MOSES): A Benchmarking Platform for Molecular Generation Models
Home-page: UNKNOWN
Author: Insilico Medicine
Author-email: moses@insilico.com
License: MIT
Platform: UNKNOWN
Requires-Python: >=3.5.0
Requires-Dist: tqdm (>=4.26.0)
Requires-Dist: matplotlib (>=3.0.0)
Requires-Dist: numpy (>=1.15)
Requires-Dist: pandas (>=0.25)
Requires-Dist: scipy (>=1.1.0)
Requires-Dist: torch (>=1.1.0)
Requires-Dist: fcd-torch (>=1.0.5)
Requires-Dist: seaborn (>=0.9.0)
Requires-Dist: pomegranate (==0.12.0)
